locate_pixelcolor_numba/README.md
locate_pixelcolor_numba/__init__.py
locate_pixelcolor_numba/requirements.txt
locate_pixelcolor_numba/searchcolorsnumba.pyd
locate_pixelcolor_numba/thirdparty.json
locate_pixelcolor_numba-0.11.dist-info/LICENSE.rst
locate_pixelcolor_numba-0.11.dist-info/METADATA
locate_pixelcolor_numba-0.11.dist-info/WHEEL
locate_pixelcolor_numba-0.11.dist-info/top_level.txt
locate_pixelcolor_numba-0.11.dist-info/RECORD
