Metadata-Version: 2.1
Name: locate-pixelcolor-numba
Version: 0.11
Summary: RGB search with numba - 2-3 x faster than numpy
Home-page: https://github.com/hansalemaos/locate_pixelcolor_numba
Author: Johannes Fischer
Author-email: aulasparticularesdealemaosp@gmail.com
License: MIT
Keywords: numba,aot,compiled,rgb,search
Classifier: Development Status :: 4 - Beta
Classifier: Programming Language :: Python :: 3 :: Only
Classifier: Programming Language :: Python :: 3.10
Classifier: Topic :: Software Development :: Libraries :: Python Modules
Classifier: Topic :: Utilities
License-File: LICENSE.rst
Requires-Dist: numpy
